{
  "path": "/projects/original-syndicate",
  "sourceUrl": "https://www.haggard.design/projects/original-syndicate",
  "title": "Original Syndicate",
  "bodyClass": "",
  "ogImage": "/assets/site/c7756f4b9c-67e58af46c89827ed9ca2d17_OG-IMG.webp",
  "htmlFile": "projects/original-syndicate.html",
  "lastMigrated": "2026-05-28T05:19:48.331Z",
  "description": "Original Syndicate needed to make advanced production feel available to brands, agencies, and individual talent without losing its future-facing edge. The brand gives creators a clearer sense of the tools, workflows, and partnership behind the offering, positioning the studio as both expert and accelerator."
}
